{
    "schema_version": "1.1",
    "type_definitions": [
        {
            "metadata": {
                "relations": {
                    "administrator": {
                        "directly_related_user_types": [
                            {
                                "type": "serviceaccount"
                            },
                            {
                                "type": "serviceaccount",
                                "wildcard": {}
                            },
                            {
                                "type": "user"
                            },
                            {
                                "type": "user",
                                "wildcard": {}
                            },
                            {
                                "relation": "member",
                                "type": "group"
                            }
                        ]
                    },
                    "consumer": {
                        "directly_related_user_types": [
                            {
                                "type": "serviceaccount"
                            },
                            {
                                "type": "serviceaccount",
                                "wildcard": {}
                            },
                            {
                                "type": "user"
                            },
                            {
                                "type": "user",
                                "wildcard": {}
                            },
                            {
                                "relation": "member",
                                "type": "group"
                            }
                        ]
                    },
                    "model": {
                        "directly_related_user_types": [
                            {
                                "type": "model"
                            }
                        ]
                    },
                    "reader": {
                        "directly_related_user_types": [
                            {
                                "type": "serviceaccount"
                            },
                            {
                                "type": "serviceaccount",
                                "wildcard": {}
                            },
                            {
                                "type": "user"
                            },
                            {
                                "type": "user",
                                "wildcard": {}
                            },
                            {
                                "relation": "member",
                                "type": "group"
                            }
                        ]
                    }
                }
            },
            "relations": {
                "administrator": {
                    "union": {
                        "child": [
                            {
                                "this": {}
                            },
                            {
                                "tupleToUserset": {
                                    "computedUserset": {
                                        "relation": "administrator"
                                    },
                                    "tupleset": {
                                        "relation": "model"
                                    }
                                }
                            }
                        ]
                    }
                },
                "consumer": {
                    "union": {
                        "child": [
                            {
                                "this": {}
                            },
                            {
                                "computedUserset": {
                                    "relation": "administrator"
                                }
                            }
                        ]
                    }
                },
                "model": {
                    "this": {}
                },
                "reader": {
                    "union": {
                        "child": [
                            {
                                "this": {}
                            },
                            {
                                "computedUserset": {
                                    "relation": "consumer"
                                }
                            }
                        ]
                    }
                }
            },
            "type": "applicationoffer"
        },
        {
            "metadata": {
                "relations": {
                    "administrator": {
                        "directly_related_user_types": [
                            {
                                "type": "serviceaccount"
                            },
                            {
                                "type": "serviceaccount",
                                "wildcard": {}
                            },
                            {
                                "type": "user"
                            },
                            {
                                "type": "user",
                                "wildcard": {}
                            },
                            {
                                "relation": "member",
                                "type": "group"
                            }
                        ]
                    },
                    "can_addmodel": {
                        "directly_related_user_types": [
                            {
                                "type": "serviceaccount"
                            },
                            {
                                "type": "serviceaccount",
                                "wildcard": {}
                            },
                            {
                                "type": "user"
                            },
                            {
                                "type": "user",
                                "wildcard": {}
                            },
                            {
                                "relation": "member",
                                "type": "group"
                            }
                        ]
                    },
                    "controller": {
                        "directly_related_user_types": [
                            {
                                "type": "controller"
                            }
                        ]
                    }
                }
            },
            "relations": {
                "administrator": {
                    "union": {
                        "child": [
                            {
                                "this": {}
                            },
                            {
                                "tupleToUserset": {
                                    "computedUserset": {
                                        "relation": "administrator"
                                    },
                                    "tupleset": {
                                        "relation": "controller"
                                    }
                                }
                            }
                        ]
                    }
                },
                "can_addmodel": {
                    "union": {
                        "child": [
                            {
                                "this": {}
                            },
                            {
                                "computedUserset": {
                                    "relation": "administrator"
                                }
                            }
                        ]
                    }
                },
                "controller": {
                    "this": {}
                }
            },
            "type": "cloud"
        },
        {
            "metadata": {
                "relations": {
                    "administrator": {
                        "directly_related_user_types": [
                            {
                                "type": "user"
                            },
                            {
                                "type": "user",
                                "wildcard": {}
                            },
                            {
                                "relation": "member",
                                "type": "group"
                            }
                        ]
                    },
                    "audit_log_viewer": {
                        "directly_related_user_types": [
                            {
                                "type": "user"
                            },
                            {
                                "type": "user",
                                "wildcard": {}
                            },
                            {
                                "relation": "member",
                                "type": "group"
                            }
                        ]
                    },
                    "controller": {
                        "directly_related_user_types": [
                            {
                                "type": "controller"
                            }
                        ]
                    }
                }
            },
            "relations": {
                "administrator": {
                    "union": {
                        "child": [
                            {
                                "this": {}
                            },
                            {
                                "tupleToUserset": {
                                    "computedUserset": {
                                        "relation": "administrator"
                                    },
                                    "tupleset": {
                                        "relation": "controller"
                                    }
                                }
                            }
                        ]
                    }
                },
                "audit_log_viewer": {
                    "union": {
                        "child": [
                            {
                                "this": {}
                            },
                            {
                                "computedUserset": {
                                    "relation": "administrator"
                                }
                            }
                        ]
                    }
                },
                "controller": {
                    "this": {}
                }
            },
            "type": "controller"
        },
        {
            "metadata": {
                "relations": {
                    "member": {
                        "directly_related_user_types": [
                            {
                                "type": "user"
                            },
                            {
                                "type": "user",
                                "wildcard": {}
                            },
                            {
                                "relation": "member",
                                "type": "group"
                            }
                        ]
                    }
                }
            },
            "relations": {
                "member": {
                    "this": {}
                }
            },
            "type": "group"
        },
        {
            "metadata": {
                "relations": {
                    "administrator": {
                        "directly_related_user_types": [
                            {
                                "type": "serviceaccount"
                            },
                            {
                                "type": "serviceaccount",
                                "wildcard": {}
                            },
                            {
                                "type": "user"
                            },
                            {
                                "type": "user",
                                "wildcard": {}
                            },
                            {
                                "relation": "member",
                                "type": "group"
                            }
                        ]
                    },
                    "controller": {
                        "directly_related_user_types": [
                            {
                                "type": "controller"
                            }
                        ]
                    },
                    "reader": {
                        "directly_related_user_types": [
                            {
                                "type": "serviceaccount"
                            },
                            {
                                "type": "serviceaccount",
                                "wildcard": {}
                            },
                            {
                                "type": "user"
                            },
                            {
                                "type": "user",
                                "wildcard": {}
                            },
                            {
                                "relation": "member",
                                "type": "group"
                            }
                        ]
                    },
                    "writer": {
                        "directly_related_user_types": [
                            {
                                "type": "serviceaccount"
                            },
                            {
                                "type": "serviceaccount",
                                "wildcard": {}
                            },
                            {
                                "type": "user"
                            },
                            {
                                "type": "user",
                                "wildcard": {}
                            },
                            {
                                "relation": "member",
                                "type": "group"
                            }
                        ]
                    }
                }
            },
            "relations": {
                "administrator": {
                    "union": {
                        "child": [
                            {
                                "this": {}
                            },
                            {
                                "tupleToUserset": {
                                    "computedUserset": {
                                        "relation": "administrator"
                                    },
                                    "tupleset": {
                                        "relation": "controller"
                                    }
                                }
                            }
                        ]
                    }
                },
                "controller": {
                    "this": {}
                },
                "reader": {
                    "union": {
                        "child": [
                            {
                                "this": {}
                            },
                            {
                                "computedUserset": {
                                    "relation": "writer"
                                }
                            }
                        ]
                    }
                },
                "writer": {
                    "union": {
                        "child": [
                            {
                                "this": {}
                            },
                            {
                                "computedUserset": {
                                    "relation": "administrator"
                                }
                            }
                        ]
                    }
                }
            },
            "type": "model"
        },
        {
            "type": "user"
        },
        {
            "metadata": {
                "relations": {
                    "administator": {
                        "directly_related_user_types": [
                            {
                                "type": "serviceaccount"
                            },
                            {
                                "type": "serviceaccount",
                                "wildcard": {}
                            },
                            {
                                "type": "user"
                            },
                            {
                                "type": "user",
                                "wildcard": {}
                            },
                            {
                                "relation": "member",
                                "type": "group"
                            }
                        ]
                    }
                }
            },
            "relations": {
                "administator": {
                    "this": {}
                }
            },
            "type": "serviceaccount"
        }
    ]
}
